world_bank_mcp_server/__init__.py
world_bank_mcp_server/server.py
world_bank_mcp_server-0.1.0.dist-info/METADATA
world_bank_mcp_server-0.1.0.dist-info/WHEEL
world_bank_mcp_server-0.1.0.dist-info/entry_points.txt
world_bank_mcp_server-0.1.0.dist-info/top_level.txt
world_bank_mcp_server-0.1.0.dist-info/RECORD
